regobslib/__init__.py
regobslib/aps.py
regobslib/connection.py
regobslib/misc.py
regobslib/region.py
regobslib/submit.py
regobslib/types.py
regobslib/varsom.py
regobslib-1.0.11.dist-info/licenses/LICENSE
regobslib-1.0.11.dist-info/METADATA
regobslib-1.0.11.dist-info/WHEEL
regobslib-1.0.11.dist-info/top_level.txt
regobslib-1.0.11.dist-info/RECORD
