Metadata-Version: 2.4
Name: regobslib
Version: 1.0.11
Summary: Client library for Regobs
Home-page: https://github.com/NVE/regobslib
Author: Aron Widforss
Author-email: arwi@nve.no
Project-URL: API Documentation, http://api.nve.no/doc/regobs/
Classifier: Programming Language :: Python :: 3
Classifier: License :: OSI Approved :: MIT License
Classifier: Operating System :: OS Independent
Requires-Python: >=3.6
License-File: LICENSE
Requires-Dist: requests
Requires-Dist: pytz
Requires-Dist: pandas
Requires-Dist: numpy
Dynamic: license-file
